LICENSE
MANIFEST.in
README.rst
requirements.txt
setup.py
django_persistent_file_widget.egg-info/PKG-INFO
django_persistent_file_widget.egg-info/SOURCES.txt
django_persistent_file_widget.egg-info/dependency_links.txt
django_persistent_file_widget.egg-info/top_level.txt
persistent_widget/__init__.py
persistent_widget/__init__.pyc
persistent_widget/models.py
persistent_widget/models.pyc
persistent_widget/tests.py
persistent_widget/utils.py
persistent_widget/utils.pyc
persistent_widget/widgets.py
persistent_widget/widgets.pyc
persistent_widget/templates/persistent_widget/persistent_file_widget.html