Metadata-Version: 1.0
Name: django-persistent-file-widget
Version: 0.0.1
Summary: A django form file widget that persists between erroneous form submissions!
Home-page: https://github.com/sandersnewmedia/django-persistent-file-widget
Author: Elijah Rutschman, Brent Sanders, Scott Meisburger
Author-email: info+django-persistent-file-widget@sandersnewmedia.com
License: 
